pyloopkit/__init__.py
pyloopkit/carb_math.py
pyloopkit/carb_status.py
pyloopkit/carb_store.py
pyloopkit/date.py
pyloopkit/depreciated/glucose_effect.py
pyloopkit/depreciated/glucose_effect_velocity.py
pyloopkit/docs/pyloopkit_documentation.md
pyloopkit/dose.py
pyloopkit/dose_entry.py
pyloopkit/dose_math.py
pyloopkit/dose_store.py
pyloopkit/environment.yml
pyloopkit/example_files/custom-scenario-table-template-complex.csv.html
pyloopkit/example_files/example_from_previous_run.json
pyloopkit/example_files/example_issue_report_1-output.html
pyloopkit/example_files/example_issue_report_1-output.json
pyloopkit/example_files/example_issue_report_1.json
pyloopkit/example_files/example_issue_report_2-output.json
pyloopkit/example_files/example_issue_report_2.json
pyloopkit/example_files/example_issue_report_3-output.json
pyloopkit/example_files/example_issue_report_3.json
pyloopkit/example_files/example_issue_report_4-output.json
pyloopkit/example_files/example_issue_report_4.json
pyloopkit/exponential_insulin_model.py
pyloopkit/generate_graphs.py
pyloopkit/glucose_math.py
pyloopkit/glucose_store.py
pyloopkit/input_validation_tools.py
pyloopkit/insulin_math.py
pyloopkit/loop_data_manager.py
pyloopkit/loop_math.py
pyloopkit/pyloop_parser.py
pyloopkit/requirements.txt
pyloopkit/tests/fixtures/LoopKit/basal.json
pyloopkit/walsh_insulin_model.py
opsb_pyloopkit-0.1.0.dist-info/LICENSE
opsb_pyloopkit-0.1.0.dist-info/WHEEL
opsb_pyloopkit-0.1.0.dist-info/METADATA
opsb_pyloopkit-0.1.0.dist-info/RECORD
