Metadata-Version: 2.1
Name: opsb-pyloopkit
Version: 0.1.0
Summary: 
Home-page: https://github.com/tidepool-org/PyLoopKit
License: BSD
Author: Oliver Searle-Barnes
Author-email: oliver@opsb.co.uk
Requires-Python: >=3.9,<4.0
Classifier: License :: Other/Proprietary License
Classifier: Programming Language :: Python :: 3
Classifier: Programming Language :: Python :: 3.9
Classifier: Programming Language :: Python :: 3.10
Requires-Dist: numpy (>=1.23.2,<2.0.0)
